runpodpy/__init__.py
runpodpy/__main__.py
runpodpy/cli.py
runpodpy/config.py
runpodpy/runpod.py
RunPodPy-0.3.3.dist-info/LICENSE
RunPodPy-0.3.3.dist-info/METADATA
RunPodPy-0.3.3.dist-info/WHEEL
RunPodPy-0.3.3.dist-info/entry_points.txt
RunPodPy-0.3.3.dist-info/top_level.txt
RunPodPy-0.3.3.dist-info/RECORD
