Metadata-Version: 2.1
Name: RunPodPy
Version: 0.3.3
Summary: A Python API Wrapper and CLI for RunPod.io
Author-email: Opentensor Foundation <cameron@opentensor.ai>
License: The MIT License (MIT)
Project-URL: Homepage, https://github.com/opentensor/RunPodPy
Keywords: runpod,wrapper,api
Classifier: License :: OSI Approved :: MIT License
Classifier: Programming Language :: Python
Classifier: Programming Language :: Python :: 3
Requires-Python: >=3.9
License-File: LICENSE
Requires-Dist: ruamel.yaml (>=0.17.21)
Requires-Dist: munch (>=2.5.0)
Requires-Dist: gql[all] (>=3.3.0)
Requires-Dist: tabulate (>=0.8.10)
Requires-Dist: loguru (>=0.6.0)
Requires-Dist: tomli ; python_version < "3.11"
Provides-Extra: dev
Requires-Dist: black ; extra == 'dev'
Requires-Dist: pip-tools ; extra == 'dev'
Requires-Dist: pytest ; extra == 'dev'
